streamlit_pianoroll/__init__.py
streamlit_pianoroll/example.py
streamlit_pianoroll/example_maestro.py
streamlit_pianoroll/frontend/build/.styles.css.swp
streamlit_pianoroll/frontend/build/asset-manifest.json
streamlit_pianoroll/frontend/build/bootstrap.min.css
streamlit_pianoroll/frontend/build/color.svg
streamlit_pianoroll/frontend/build/index.html
streamlit_pianoroll/frontend/build/styles.css
streamlit_pianoroll/frontend/build/static/js/main.14228cde.js
streamlit_pianoroll/frontend/build/static/js/main.14228cde.js.LICENSE.txt
streamlit_pianoroll/frontend/build/static/js/main.14228cde.js.map
streamlit_pianoroll/frontend/build/static/js/main.56f5e72d.js
streamlit_pianoroll/frontend/build/static/js/main.56f5e72d.js.LICENSE.txt
streamlit_pianoroll/frontend/build/static/js/main.56f5e72d.js.map
streamlit_pianoroll/frontend/build/static/js/main.ca53dd4a.js
streamlit_pianoroll/frontend/build/static/js/main.ca53dd4a.js.LICENSE.txt
streamlit_pianoroll/frontend/build/static/js/main.ca53dd4a.js.map
streamlit_pianoroll/frontend/build/static/js/main.dfee1b5f.js
streamlit_pianoroll/frontend/build/static/js/main.dfee1b5f.js.LICENSE.txt
streamlit_pianoroll/frontend/build/static/js/main.dfee1b5f.js.map
streamlit_pianoroll-0.7.4.dist-info/METADATA
streamlit_pianoroll-0.7.4.dist-info/WHEEL
streamlit_pianoroll-0.7.4.dist-info/top_level.txt
streamlit_pianoroll-0.7.4.dist-info/RECORD
