Metadata-Version: 2.1
Name: streamlit-pianoroll
Version: 0.7.4
Summary: Streamlit component that allows you to play piano
Home-page: https://github.com/Nospoko/streamlit-pianoroll
Author: Bathilda Bagshot
Author-email: tomek@epr-labs.com
Requires-Python: >=3.7
Requires-Dist: streamlit (>=0.63)
Requires-Dist: fortepyan
Provides-Extra: devel
Requires-Dist: wheel ; extra == 'devel'
Requires-Dist: pytest (==7.4.0) ; extra == 'devel'
Requires-Dist: playwright (==1.36.0) ; extra == 'devel'
Requires-Dist: requests (==2.31.0) ; extra == 'devel'
Requires-Dist: pytest-playwright-snapshot (==1.0) ; extra == 'devel'
Requires-Dist: pytest-rerunfailures (==12.0) ; extra == 'devel'
